libmogra/.DS_Store
libmogra/__init__.py
libmogra/datatypes.py
libmogra/raagfinder/__init__.py
libmogra/raagfinder/main.py
libmogra/raagfinder/parse.py
libmogra/raagfinder/parse_tanaranga_backup.py
libmogra/raagfinder/raags.bkp.pkl
libmogra/raagfinder/raags.pkl
libmogra/shrutidata/hypothesized_gt_3_5.pkl
libmogra/shrutidata/make_tonnetz.ipynb
libmogra/tonnetz.py
libmogra-0.3.4.dist-info/LICENSE
libmogra-0.3.4.dist-info/METADATA
libmogra-0.3.4.dist-info/WHEEL
libmogra-0.3.4.dist-info/entry_points.txt
libmogra-0.3.4.dist-info/RECORD
